mijin_openapi_client/__init__.py
mijin_openapi_client/api_client.py
mijin_openapi_client/api_response.py
mijin_openapi_client/configuration.py
mijin_openapi_client/exceptions.py
mijin_openapi_client/rest.py
mijin_openapi_client/api/__init__.py
mijin_openapi_client/api/account_routes_api.py
mijin_openapi_client/api/block_routes_api.py
mijin_openapi_client/api/chain_routes_api.py
mijin_openapi_client/api/finalization_routes_api.py
mijin_openapi_client/api/hash_lock_routes_api.py
mijin_openapi_client/api/metadata_routes_api.py
mijin_openapi_client/api/mosaic_routes_api.py
mijin_openapi_client/api/multisig_routes_api.py
mijin_openapi_client/api/namespace_routes_api.py
mijin_openapi_client/api/network_routes_api.py
mijin_openapi_client/api/node_routes_api.py
mijin_openapi_client/api/receipt_routes_api.py
mijin_openapi_client/api/restriction_account_routes_api.py
mijin_openapi_client/api/restriction_mosaic_routes_api.py
mijin_openapi_client/api/secret_lock_routes_api.py
mijin_openapi_client/api/transaction_routes_api.py
mijin_openapi_client/api/transaction_status_routes_api.py
mijin_openapi_client/models/__init__.py
mijin_openapi_client/models/account_address_restriction_transaction_body_dto.py
mijin_openapi_client/models/account_address_restriction_transaction_dto.py
mijin_openapi_client/models/account_dto.py
mijin_openapi_client/models/account_ids.py
mijin_openapi_client/models/account_info_dto.py
mijin_openapi_client/models/account_key_link_network_properties_dto.py
mijin_openapi_client/models/account_key_link_transaction_body_dto.py
mijin_openapi_client/models/account_key_link_transaction_dto.py
mijin_openapi_client/models/account_key_type_flags_enum.py
mijin_openapi_client/models/account_link_public_key_dto.py
mijin_openapi_client/models/account_link_voting_key_dto.py
mijin_openapi_client/models/account_link_voting_keys_dto.py
mijin_openapi_client/models/account_metadata_transaction_body_dto.py
mijin_openapi_client/models/account_metadata_transaction_dto.py
mijin_openapi_client-1.0.2.dist-info/METADATA
mijin_openapi_client-1.0.2.dist-info/WHEEL
mijin_openapi_client-1.0.2.dist-info/top_level.txt
mijin_openapi_client-1.0.2.dist-info/RECORD
