Metadata-Version: 2.4
Name: mijin_openapi_client
Version: 1.0.2
Summary: OpenAPI client generated
Author-email: Techbureau Contributors <development@techbureau.jp>
Requires-Python: >=3.9
Requires-Dist: urllib3<3.0.0,>=1.25.3
Requires-Dist: python-dateutil>=2.8.2
Requires-Dist: pydantic>=2
Requires-Dist: typing-extensions>=4.7.1
